setup.cfg
setup.py
generic_report_generator_redshift/RedshiftDropTempTableStrategy.py
generic_report_generator_redshift/RedshiftPersistenceStrategy.py
generic_report_generator_redshift/RedshiftReportGeneratorFactory.py
generic_report_generator_redshift/RedshiftResultDownloadStrategy.py
generic_report_generator_redshift/__init__.py
generic_report_generator_redshift.egg-info/PKG-INFO
generic_report_generator_redshift.egg-info/SOURCES.txt
generic_report_generator_redshift.egg-info/dependency_links.txt
generic_report_generator_redshift.egg-info/requires.txt
generic_report_generator_redshift.egg-info/top_level.txt
generic_report_generator_redshift/model/AWSCredential.py
generic_report_generator_redshift/model/RedshiftDBPersistent.py
generic_report_generator_redshift/model/__init__.py